[
  {
    "Description": "WORLD WAR 2 GLIDERS ASSTD DESIGNS",
    "stock_code": "84077",
    "total_quantity": 110138,
    "total_revenue": 25259.899999999998,
    "average_price": 0.29,
    "orders": 1019
  },
  {
    "Description": "WHITE HANGING HEART T-LIGHT HOLDER",
    "stock_code": "85123A",
    "total_quantity": 96683,
    "total_revenue": 266923.55,
    "average_price": 2.95,
    "orders": 5455
  },
  {
    "Description": "ASSORTED COLOUR BIRD ORNAMENT",
    "stock_code": "84879",
    "total_quantity": 81809,
    "total_revenue": 132187.91999999998,
    "average_price": 1.69,
    "orders": 2807
  },
  {
    "Description": "PAPER CRAFT , LITTLE BIRDIE",
    "stock_code": "23843",
    "total_quantity": 80995,
    "total_revenue": 168469.6,
    "average_price": 2.08,
    "orders": 1
  },
  {
    "Description": "JUMBO BAG RED RETROSPOT",
    "stock_code": "85099B",
    "total_quantity": 79279,
    "total_revenue": 150935.56,
    "average_price": 2.08,
    "orders": 3269
  },
  {
    "Description": "MEDIUM CERAMIC TOP STORAGE JAR",
    "stock_code": "23166",
    "total_quantity": 78033,
    "total_revenue": 81700.92000000001,
    "average_price": 1.25,
    "orders": 247
  },
  {
    "Description": "BROCADE RING PURSE",
    "stock_code": "17003",
    "total_quantity": 71430,
    "total_revenue": 14959.19,
    "average_price": 0.29,
    "orders": 456
  },
  {
    "Description": "PACK OF 60 PINK PAISLEY CAKE CASES",
    "stock_code": "21977",
    "total_quantity": 56794,
    "total_revenue": 28490.98,
    "average_price": 0.55,
    "orders": 1993
  },
  {
    "Description": "60 TEATIME FAIRY CAKE CASES",
    "stock_code": "84991",
    "total_quantity": 54716,
    "total_revenue": 27404.22,
    "average_price": 0.55,
    "orders": 2127
  },
  {
    "Description": "SMALL POPCORN HOLDER",
    "stock_code": "22197",
    "total_quantity": 49948,
    "total_revenue": 44090.13,
    "average_price": 0.85,
    "orders": 1407
  },
  {
    "Description": "PACK OF 72 RETROSPOT CAKE CASES",
    "stock_code": "21212",
    "total_quantity": 49805,
    "total_revenue": 28927.920000000002,
    "average_price": 0.55,
    "orders": 1708
  },
  {
    "Description": "PACK OF 72 RETRO SPOT CAKE CASES",
    "stock_code": "21212",
    "total_quantity": 46755,
    "total_revenue": 24069.280000000002,
    "average_price": 0.55,
    "orders": 1410
  },
  {
    "Description": "MINI PAINT SET VINTAGE",
    "stock_code": "22492",
    "total_quantity": 44405,
    "total_revenue": 28284.79,
    "average_price": 0.65,
    "orders": 714
  },
  {
    "Description": "ASSORTED COLOURS SILK FAN",
    "stock_code": "15036",
    "total_quantity": 44365,
    "total_revenue": 33041.55,
    "average_price": 0.83,
    "orders": 991
  },
  {
    "Description": "COLOUR GLASS T-LIGHT HOLDER HANGING",
    "stock_code": "84755",
    "total_quantity": 40839,
    "total_revenue": 25475.050000000003,
    "average_price": 0.65,
    "orders": 1259
  },
  {
    "Description": "VICTORIAN GLASS HANGING T-LIGHT",
    "stock_code": "22178",
    "total_quantity": 40748,
    "total_revenue": 53330.49,
    "average_price": 1.25,
    "orders": 1816
  },
  {
    "Description": "PACK OF 72 SKULL CAKE CASES",
    "stock_code": "21213",
    "total_quantity": 40733,
    "total_revenue": 21734.850000000002,
    "average_price": 0.55,
    "orders": 1481
  },
  {
    "Description": "PACK OF 12 LONDON TISSUES",
    "stock_code": "22616",
    "total_quantity": 40163,
    "total_revenue": 12764.06,
    "average_price": 0.29,
    "orders": 825
  },
  {
    "Description": "GIRLS ALPHABET IRON ON PATCHES",
    "stock_code": "84568",
    "total_quantity": 38574,
    "total_revenue": 8062.71,
    "average_price": 0.42,
    "orders": 310
  },
  {
    "Description": "RED  HARMONICA IN BOX",
    "stock_code": "21915",
    "total_quantity": 38191,
    "total_revenue": 44808.8,
    "average_price": 1.25,
    "orders": 1025
  },
  {
    "Description": "STRAWBERRY CERAMIC TRINKET BOX",
    "stock_code": "21232",
    "total_quantity": 37610,
    "total_revenue": 48626.76,
    "average_price": 1.25,
    "orders": 2310
  },
  {
    "Description": "JUMBO BAG STRAWBERRY",
    "stock_code": "85099F",
    "total_quantity": 37337,
    "total_revenue": 69565.89,
    "average_price": 1.95,
    "orders": 1855
  },
  {
    "Description": "POPCORN HOLDER",
    "stock_code": "22197",
    "total_quantity": 36761,
    "total_revenue": 34298.87,
    "average_price": 0.85,
    "orders": 803
  },
  {
    "Description": "PAPER CHAIN KIT 50'S CHRISTMAS",
    "stock_code": "22086",
    "total_quantity": 36581,
    "total_revenue": 123141.54000000001,
    "average_price": 2.95,
    "orders": 2018
  },
  {
    "Description": "72 SWEETHEART FAIRY CAKE CASES",
    "stock_code": "84992",
    "total_quantity": 35438,
    "total_revenue": 17585.16,
    "average_price": 0.55,
    "orders": 1460
  },
  {
    "Description": "PACK OF 12 SUKI TISSUES",
    "stock_code": "21982",
    "total_quantity": 32827,
    "total_revenue": 10589.349999999999,
    "average_price": 0.29,
    "orders": 718
  },
  {
    "Description": "ROTATING SILVER ANGELS T-LIGHT HLDR",
    "stock_code": "84347",
    "total_quantity": 32525,
    "total_revenue": 74448.92,
    "average_price": 2.55,
    "orders": 756
  },
  {
    "Description": "PACK OF 60 DINOSAUR CAKE CASES",
    "stock_code": "21975",
    "total_quantity": 31575,
    "total_revenue": 15381.95,
    "average_price": 0.55,
    "orders": 1303
  },
  {
    "Description": "JUMBO  BAG BAROQUE BLACK WHITE",
    "stock_code": "85099C",
    "total_quantity": 31266,
    "total_revenue": 60377.49,
    "average_price": 1.95,
    "orders": 1878
  },
  {
    "Description": "RABBIT NIGHT LIGHT",
    "stock_code": "23084",
    "total_quantity": 30788,
    "total_revenue": 66964.99,
    "average_price": 2.08,
    "orders": 994
  },
  {
    "Description": "HANGING JAM JAR T-LIGHT HOLDER",
    "stock_code": "71459",
    "total_quantity": 30764,
    "total_revenue": 24894.46,
    "average_price": 0.85,
    "orders": 925
  },
  {
    "Description": "SMALL CHINESE STYLE SCISSOR",
    "stock_code": "16014",
    "total_quantity": 30370,
    "total_revenue": 9839.4,
    "average_price": 0.42,
    "orders": 93
  },
  {
    "Description": "RED TOADSTOOL LED NIGHT LIGHT",
    "stock_code": "21731",
    "total_quantity": 29715,
    "total_revenue": 49539.689999999995,
    "average_price": 1.65,
    "orders": 1537
  },
  {
    "Description": "JUMBO STORAGE BAG SUKI",
    "stock_code": "21931",
    "total_quantity": 29503,
    "total_revenue": 62285.28,
    "average_price": 1.95,
    "orders": 2329
  },
  {
    "Description": "HEART OF WICKER SMALL",
    "stock_code": "22469",
    "total_quantity": 29037,
    "total_revenue": 51127.759999999995,
    "average_price": 1.65,
    "orders": 2151
  },
  {
    "Description": "60 CAKE CASES VINTAGE CHRISTMAS",
    "stock_code": "22952",
    "total_quantity": 28744,
    "total_revenue": 17329.49,
    "average_price": 0.55,
    "orders": 1039
  },
  {
    "Description": "PARTY BUNTING",
    "stock_code": "47566",
    "total_quantity": 28378,
    "total_revenue": 149187.05000000002,
    "average_price": 4.95,
    "orders": 2674
  },
  {
    "Description": "CHARLOTTE BAG SUKI DESIGN",
    "stock_code": "22355",
    "total_quantity": 28283,
    "total_revenue": 42834.299999999996,
    "average_price": 0.85,
    "orders": 1403
  },
  {
    "Description": "VINTAGE SNAP CARDS",
    "stock_code": "21790",
    "total_quantity": 27942,
    "total_revenue": 24095.6,
    "average_price": 0.85,
    "orders": 1888
  },
  {
    "Description": "PLACE SETTING WHITE HEART",
    "stock_code": "22151",
    "total_quantity": 27897,
    "total_revenue": 11754.85,
    "average_price": 0.42,
    "orders": 716
  },
  {
    "Description": "JUMBO SHOPPER VINTAGE RED PAISLEY",
    "stock_code": "22411",
    "total_quantity": 27732,
    "total_revenue": 58275.45,
    "average_price": 1.95,
    "orders": 2192
  },
  {
    "Description": "REGENCY CAKESTAND 3 TIER",
    "stock_code": "22423",
    "total_quantity": 27577,
    "total_revenue": 344563.25,
    "average_price": 12.75,
    "orders": 3918
  },
  {
    "Description": "HANGING HEART ZINC T-LIGHT HOLDER",
    "stock_code": "84970S",
    "total_quantity": 27231,
    "total_revenue": 22946.039999999997,
    "average_price": 0.85,
    "orders": 1523
  },
  {
    "Description": "LUNCH BAG  BLACK SKULL.",
    "stock_code": "20727",
    "total_quantity": 27126,
    "total_revenue": 46422.49,
    "average_price": 1.65,
    "orders": 2351
  },
  {
    "Description": "PACK OF 12 WOODLAND TISSUES",
    "stock_code": "21981",
    "total_quantity": 26472,
    "total_revenue": 7213.86,
    "average_price": 0.29,
    "orders": 553
  },
  {
    "Description": "JUMBO BAG PINK VINTAGE PAISLEY",
    "stock_code": "21929",
    "total_quantity": 25954,
    "total_revenue": 50334.1,
    "average_price": 1.95,
    "orders": 1619
  },
  {
    "Description": "PACK OF 12 HEARTS DESIGN TISSUES",
    "stock_code": "21985",
    "total_quantity": 25708,
    "total_revenue": 9032.96,
    "average_price": 0.29,
    "orders": 919
  },
  {
    "Description": "BLACK AND WHITE PAISLEY FLOWER MUG",
    "stock_code": "37410",
    "total_quantity": 25707,
    "total_revenue": 3288.65,
    "average_price": 1.25,
    "orders": 33
  },
  {
    "Description": "JUMBO BAG PINK POLKADOT",
    "stock_code": "22386",
    "total_quantity": 25627,
    "total_revenue": 50847.8,
    "average_price": 2.08,
    "orders": 1443
  },
  {
    "Description": "PACK OF 12 PINK PAISLEY TISSUES",
    "stock_code": "21984",
    "total_quantity": 25509,
    "total_revenue": 7077.05,
    "average_price": 0.29,
    "orders": 432
  },
  {
    "Description": "WOODLAND CHARLOTTE BAG",
    "stock_code": "20719",
    "total_quantity": 24945,
    "total_revenue": 28287.32,
    "average_price": 0.85,
    "orders": 1573
  },
  {
    "Description": "LUNCH BAG CARS BLUE",
    "stock_code": "20728",
    "total_quantity": 24892,
    "total_revenue": 42784.74,
    "average_price": 1.65,
    "orders": 2067
  },
  {
    "Description": "ASSORTED FLOWER COLOUR \"LEIS\"",
    "stock_code": "84212",
    "total_quantity": 24801,
    "total_revenue": 11966.04,
    "average_price": 0.65,
    "orders": 277
  },
  {
    "Description": "ANTIQUE SILVER TEA GLASS ETCHED",
    "stock_code": "84946",
    "total_quantity": 23376,
    "total_revenue": 31918.100000000002,
    "average_price": 1.25,
    "orders": 1080
  },
  {
    "Description": "PLEASE ONE PERSON METAL SIGN",
    "stock_code": "21181",
    "total_quantity": 23248,
    "total_revenue": 47133.55,
    "average_price": 2.1,
    "orders": 1632
  },
  {
    "Description": "ASSTD DESIGN BUBBLE GUM RING",
    "stock_code": "84270",
    "total_quantity": 23013,
    "total_revenue": 4840.47,
    "average_price": 0.21,
    "orders": 476
  },
  {
    "Description": "LUNCH BAG RED RETROSPOT",
    "stock_code": "20725",
    "total_quantity": 22799,
    "total_revenue": 42135.88,
    "average_price": 1.65,
    "orders": 1837
  },
  {
    "Description": "PACK OF 12 RED SPOTTY TISSUES",
    "stock_code": "21980",
    "total_quantity": 22723,
    "total_revenue": 5982.39,
    "average_price": 0.29,
    "orders": 271
  },
  {
    "Description": "MULTI COLOUR SILVER T-LIGHT HOLDER",
    "stock_code": "84945",
    "total_quantity": 22662,
    "total_revenue": 18617.8,
    "average_price": 0.85,
    "orders": 653
  },
  {
    "Description": "PINK BLUE FELT CRAFT TRINKET BOX",
    "stock_code": "20971",
    "total_quantity": 22629,
    "total_revenue": 29027.46,
    "average_price": 1.25,
    "orders": 1148
  },
  {
    "Description": "LUNCH BAG WOODLAND",
    "stock_code": "20726",
    "total_quantity": 22341,
    "total_revenue": 38949.729999999996,
    "average_price": 1.65,
    "orders": 1926
  },
  {
    "Description": "DISCO BALL CHRISTMAS DECORATION",
    "stock_code": "20668",
    "total_quantity": 21916,
    "total_revenue": 2570.81,
    "average_price": 0.12,
    "orders": 367
  },
  {
    "Description": "HANGING HEART JAR T-LIGHT HOLDER",
    "stock_code": "84978",
    "total_quantity": 21903,
    "total_revenue": 28734.82,
    "average_price": 1.25,
    "orders": 1425
  },
  {
    "Description": "PACK OF 60 SPACEBOY CAKE CASES",
    "stock_code": "22417",
    "total_quantity": 21641,
    "total_revenue": 11258.890000000001,
    "average_price": 0.55,
    "orders": 1103
  },
  {
    "Description": "SPACEBOY LUNCH BOX",
    "stock_code": "22629",
    "total_quantity": 21223,
    "total_revenue": 38750.2,
    "average_price": 1.95,
    "orders": 1368
  },
  {
    "Description": "JUMBO BAG OWLS",
    "stock_code": "20713",
    "total_quantity": 21199,
    "total_revenue": 41390.09,
    "average_price": 1.95,
    "orders": 1314
  },
  {
    "Description": "RED RETROSPOT CHARLOTTE BAG",
    "stock_code": "20724",
    "total_quantity": 20916,
    "total_revenue": 25332.739999999998,
    "average_price": 0.85,
    "orders": 1255
  },
  {
    "Description": "BOYS ALPHABET IRON ON PATCHES",
    "stock_code": "84598",
    "total_quantity": 20799,
    "total_revenue": 4360.46,
    "average_price": 0.42,
    "orders": 217
  },
  {
    "Description": "PINK CREAM FELT CRAFT TRINKET BOX",
    "stock_code": "20972",
    "total_quantity": 20761,
    "total_revenue": 25151.84,
    "average_price": 1.25,
    "orders": 1397
  },
  {
    "Description": "GIN + TONIC DIET METAL SIGN",
    "stock_code": "21175",
    "total_quantity": 20407,
    "total_revenue": 43153.93,
    "average_price": 2.1,
    "orders": 1609
  },
  {
    "Description": "ZINC METAL HEART DECORATION",
    "stock_code": "84836",
    "total_quantity": 20251,
    "total_revenue": 24805.670000000002,
    "average_price": 1.25,
    "orders": 1408
  },
  {
    "Description": "GRAND CHOCOLATECANDLE",
    "stock_code": "72741",
    "total_quantity": 20178,
    "total_revenue": 27915.129999999997,
    "average_price": 1.45,
    "orders": 920
  },
  {
    "Description": "SET/6 RED SPOTTY PAPER PLATES",
    "stock_code": "21094",
    "total_quantity": 20161,
    "total_revenue": 15723.97,
    "average_price": 0.85,
    "orders": 984
  },
  {
    "Description": "COOK WITH WINE METAL SIGN",
    "stock_code": "21166",
    "total_quantity": 20128,
    "total_revenue": 38560.16,
    "average_price": 1.95,
    "orders": 1425
  },
  {
    "Description": "BLACK RECORD COVER FRAME",
    "stock_code": "21137",
    "total_quantity": 19954,
    "total_revenue": 69329.47,
    "average_price": 3.75,
    "orders": 634
  },
  {
    "Description": "LUNCH BAG SPACEBOY DESIGN",
    "stock_code": "22382",
    "total_quantity": 19814,
    "total_revenue": 33413.79,
    "average_price": 1.65,
    "orders": 2108
  },
  {
    "Description": "SWEETHEART CERAMIC TRINKET BOX",
    "stock_code": "21231",
    "total_quantity": 19767,
    "total_revenue": 24618.13,
    "average_price": 1.25,
    "orders": 1482
  },
  {
    "Description": "PAPER CHAIN KIT VINTAGE CHRISTMAS",
    "stock_code": "22910",
    "total_quantity": 19597,
    "total_revenue": 61721.990000000005,
    "average_price": 2.95,
    "orders": 1427
  },
  {
    "Description": "BOX OF 24 COCKTAIL PARASOLS",
    "stock_code": "84692",
    "total_quantity": 19467,
    "total_revenue": 9530.48,
    "average_price": 0.42,
    "orders": 1122
  },
  {
    "Description": "VINTAGE HEADS AND TAILS CARD GAME",
    "stock_code": "21791",
    "total_quantity": 18585,
    "total_revenue": 23993.23,
    "average_price": 1.25,
    "orders": 1313
  },
  {
    "Description": "HEART OF WICKER LARGE",
    "stock_code": "22470",
    "total_quantity": 18551,
    "total_revenue": 55898.87,
    "average_price": 2.95,
    "orders": 1952
  },
  {
    "Description": "STRAWBERRY CHARLOTTE BAG",
    "stock_code": "20723",
    "total_quantity": 18485,
    "total_revenue": 20677.62,
    "average_price": 0.85,
    "orders": 1379
  },
  {
    "Description": "CREAM HEART CARD HOLDER",
    "stock_code": "22189",
    "total_quantity": 18363,
    "total_revenue": 54598.73,
    "average_price": 3.95,
    "orders": 1299
  },
  {
    "Description": "DOLLY GIRL LUNCH BOX",
    "stock_code": "22630",
    "total_quantity": 18363,
    "total_revenue": 33980.0,
    "average_price": 1.95,
    "orders": 1333
  },
  {
    "Description": "AGED GLASS SILVER T-LIGHT HOLDER",
    "stock_code": "21326",
    "total_quantity": 18356,
    "total_revenue": 11972.480000000001,
    "average_price": 0.65,
    "orders": 643
  },
  {
    "Description": "PACK OF 6 BIRDY GIFT TAGS",
    "stock_code": "22585",
    "total_quantity": 18333,
    "total_revenue": 22903.920000000002,
    "average_price": 1.25,
    "orders": 1084
  },
  {
    "Description": "LUNCH BAG RED SPOTTY",
    "stock_code": "20725",
    "total_quantity": 18143,
    "total_revenue": 30156.97,
    "average_price": 1.65,
    "orders": 1219
  },
  {
    "Description": "JAM MAKING SET PRINTED",
    "stock_code": "22961",
    "total_quantity": 18086,
    "total_revenue": 28242.89,
    "average_price": 1.45,
    "orders": 1200
  },
  {
    "Description": "PACK OF 12 TRADITIONAL CRAYONS",
    "stock_code": "22489",
    "total_quantity": 18076,
    "total_revenue": 7618.0199999999995,
    "average_price": 0.42,
    "orders": 785
  },
  {
    "Description": "RED HANGING HEART T-LIGHT HOLDER",
    "stock_code": "21733",
    "total_quantity": 17999,
    "total_revenue": 51556.97,
    "average_price": 2.95,
    "orders": 1760
  },
  {
    "Description": "JUMBO BAG WOODLAND ANIMALS",
    "stock_code": "20712",
    "total_quantity": 17957,
    "total_revenue": 38029.89,
    "average_price": 2.08,
    "orders": 1415
  },
  {
    "Description": "GROW A FLYTRAP OR SUNFLOWER IN TIN",
    "stock_code": "22693",
    "total_quantity": 17899,
    "total_revenue": 20499.08,
    "average_price": 1.25,
    "orders": 350
  },
  {
    "Description": "SINGLE HEART ZINC T-LIGHT HOLDER",
    "stock_code": "84970L",
    "total_quantity": 17884,
    "total_revenue": 17948.95,
    "average_price": 0.95,
    "orders": 1145
  },
  {
    "Description": "SET OF 20 VINTAGE CHRISTMAS NAPKINS",
    "stock_code": "22909",
    "total_quantity": 17706,
    "total_revenue": 15779.529999999999,
    "average_price": 0.85,
    "orders": 1086
  },
  {
    "Description": "FANCY FONTS BIRTHDAY WRAP",
    "stock_code": "21497",
    "total_quantity": 17625,
    "total_revenue": 7030.5,
    "average_price": 0.42,
    "orders": 485
  },
  {
    "Description": "6 RIBBONS RUSTIC CHARM",
    "stock_code": "22077",
    "total_quantity": 17569,
    "total_revenue": 32213.589999999997,
    "average_price": 1.65,
    "orders": 1751
  },
  {
    "Description": "BAG 250g SWIRLY MARBLES",
    "stock_code": "21704",
    "total_quantity": 17304,
    "total_revenue": 13347.599999999999,
    "average_price": 0.85,
    "orders": 568
  },
  {
    "Description": "JUMBO BAG SPACEBOY DESIGN",
    "stock_code": "22385",
    "total_quantity": 17227,
    "total_revenue": 32749.37,
    "average_price": 1.95,
    "orders": 1248
  },
  {
    "Description": "WOODEN PICTURE FRAME WHITE FINISH",
    "stock_code": "82482",
    "total_quantity": 17198,
    "total_revenue": 42546.58,
    "average_price": 2.55,
    "orders": 2006
  },
  {
    "Description": "HEART FILIGREE DOVE  SMALL",
    "stock_code": "22294",
    "total_quantity": 17127,
    "total_revenue": 21217.02,
    "average_price": 1.25,
    "orders": 861
  }
]